README.md
setup.py
anchor/__init__.py
anchor/anchor_base.py
anchor/anchor_explanation.py
anchor/anchor_image.py
anchor/anchor_tabular.py
anchor/anchor_text.py
anchor/utils.py
anchor_exp.egg-info/PKG-INFO
anchor_exp.egg-info/SOURCES.txt
anchor_exp.egg-info/dependency_links.txt
anchor_exp.egg-info/not-zip-safe
anchor_exp.egg-info/requires.txt
anchor_exp.egg-info/top_level.txt