Metadata-Version: 1.0
Name: anchor-exp
Version: 0.0.0.1
Summary: Anchor explanations for machine learning models
Home-page: http://github.com/marcotcr/anchor
Author: Marco Tulio Ribeiro
Author-email: marcotcr@gmail.com
License: BSD
Platform: UNKNOWN
